OptionsPricerLib/__init__.py
OptionsPricerLib/barone_adesi_whaley.py
OptionsPricerLib/black_scholes.py
OptionsPricerLib/cox_ross_rubinstein.py
OptionsPricerLib/jarrow_rudd.py
OptionsPricerLib/leisen_reimer.py
OptionsPricerLib/utils.py
OptionsPricerLib-0.1.5.dist-info/LICENSE
OptionsPricerLib-0.1.5.dist-info/METADATA
OptionsPricerLib-0.1.5.dist-info/WHEEL
OptionsPricerLib-0.1.5.dist-info/top_level.txt
OptionsPricerLib-0.1.5.dist-info/RECORD
