Metadata-Version: 2.1
Name: OptionsPricerLib
Version: 0.1.5
Summary: A library for pricing options using different models
Home-page: https://github.com/hedge0/OptionsPricerLib
Author: hedge0
Classifier: Programming Language :: Python :: 3
Classifier: License :: OSI Approved :: MIT License
Classifier: Operating System :: OS Independent
Requires-Python: >=3.6
License-File: LICENSE
Requires-Dist: numpy
Requires-Dist: numba
